fastmcp_agents/cli/__init__.py
fastmcp_agents/cli/main.py
fastmcp_agents/cli/utils.py
fastmcp_agents_cli-0.5.10.dist-info/WHEEL
fastmcp_agents_cli-0.5.10.dist-info/entry_points.txt
fastmcp_agents_cli-0.5.10.dist-info/METADATA
fastmcp_agents_cli-0.5.10.dist-info/RECORD
