Metadata-Version: 2.3
Name: fastmcp-agents-cli
Version: 0.5.10
Summary: CLI for running FastMCP and calling tools on it
Requires-Dist: cyclopts>=3.22.2
Requires-Dist: fastmcp
Requires-Dist: pyyaml>=6.0.2
Requires-Dist: rich>=14.0.0
Requires-Python: >=3.13
